[
  {"name": "Hospital General de Quito", "type": "iess", "network": "iess", "zone": "Quito", "lat": -0.1807, "lon": -78.4678, "specialty_costs": {"cardiologia": 0, "neumologia": 0, "medicina_general": 0, "neurologia": 0, "cirugia_general": 0, "emergencias": 0, "gastroenterologia": 0, "ortopedia": 0, "urologia": 0, "dermatologia": 0, "pediatria": 0, "ginecologia": 0, "traumatologia": 0, "oftalmologia": 0, "otorrinolaringologia": 0, "psiquiatria": 0, "reumatologia": 0, "endocrinologia": 0, "alergologia": 0, "cirugia_vascular": 0, "oncologia": 0, "nutricion": 0, "geriatria": 0}},
  {"name": "Hospital Carlos Andrade Marin", "type": "iess", "network": "iess", "zone": "Quito", "lat": -0.2065, "lon": -78.4908, "specialty_costs": {"cardiologia": 0, "neumologia": 0, "medicina_general": 0, "emergencias": 0, "gastroenterologia": 0, "ortopedia": 0, "neurologia": 0, "urologia": 0, "ginecologia": 0}},
  {"name": "Hospital Eugenio Espejo", "type": "public", "network": "iess", "zone": "Quito", "lat": -0.1834, "lon": -78.4665, "specialty_costs": {"cardiologia": 0, "neumologia": 0, "medicina_general": 0, "emergencias": 0, "cirugia_general": 0, "neurologia": 0, "pediatria": 0}},
  {"name": "Hospital Militar", "type": "issfa", "network": "issfa", "zone": "Quito", "lat": -0.1950, "lon": -78.4750, "specialty_costs": {"cardiologia": 0, "neumologia": 0, "medicina_general": 0, "emergencias": 0, "ortopedia": 0, "cirugia_general": 0}},
  {"name": "Clinica Metropolitan", "type": "private", "network": "bupa_red_interna", "zone": "Quito", "lat": -0.1930, "lon": -78.4815, "specialty_costs": {"cardiologia": 50, "neumologia": 45, "medicina_general": 30, "neurologia": 48, "cirugia_general": 80, "emergencias": 60, "gastroenterologia": 42, "ortopedia": 40, "urologia": 42, "dermatologia": 35, "pediatria": 30, "ginecologia": 38, "oftalmologia": 40, "otorrinolaringologia": 38, "psiquiatria": 45, "reumatologia": 42, "endocrinologia": 40, "alergologia": 38, "cirugia_vascular": 65, "oncologia": 70, "nutricion": 25, "geriatria": 35}},
  {"name": "Hospital Vithas", "type": "private", "network": "bupa_red_interna", "zone": "Quito", "lat": -0.1750, "lon": -78.4640, "specialty_costs": {"cardiologia": 55, "neumologia": 40, "medicina_general": 28, "neurologia": 50, "emergencias": 55, "gastroenterologia": 38, "ortopedia": 38, "urologia": 40, "dermatologia": 32, "pediatria": 25, "ginecologia": 35, "oftalmologia": 36, "otorrinolaringologia": 34, "psiquiatria": 42, "reumatologia": 40, "endocrinologia": 38, "alergologia": 35, "cirugia_vascular": 60, "oncologia": 68, "nutricion": 22, "geriatria": 32}},
  {"name": "Clinica Internacional", "type": "private", "network": "saludsa_red", "zone": "Quito", "lat": -0.1910, "lon": -78.4830, "specialty_costs": {"cardiologia": 52, "neumologia": 42, "medicina_general": 32, "emergencias": 58, "gastroenterologia": 40, "ortopedia": 42, "neurologia": 48, "urologia": 44, "dermatologia": 36, "pediatria": 28, "ginecologia": 36, "oftalmologia": 38, "otorrinolaringologia": 36, "psiquiatria": 46, "reumatologia": 44, "endocrinologia": 42, "alergologia": 34, "cirugia_vascular": 62, "oncologia": 72, "nutricion": 28, "geriatria": 34}},
  {"name": "Clinica San Juan de Dios", "type": "private", "network": "saludsa_red", "zone": "Quito", "lat": -0.1870, "lon": -78.4750, "specialty_costs": {"cardiologia": 48, "neumologia": 38, "medicina_general": 27, "emergencias": 50, "gastroenterologia": 36, "ortopedia": 36, "neurologia": 45, "urologia": 40, "dermatologia": 30, "pediatria": 24, "ginecologia": 33, "oftalmologia": 35, "psiquiatria": 40, "endocrinologia": 35, "alergologia": 32}},
  {"name": "Clinica Americas", "type": "private", "network": "bmi_red", "zone": "Quito", "lat": -0.1790, "lon": -78.4700, "specialty_costs": {"cardiologia": 55, "neumologia": 44, "medicina_general": 33, "emergencias": 62, "gastroenterologia": 43, "ortopedia": 42, "neurologia": 50, "urologia": 45, "dermatologia": 38, "pediatria": 30, "ginecologia": 40, "oftalmologia": 42, "otorrinolaringologia": 40, "psiquiatria": 48, "reumatologia": 44, "endocrinologia": 42, "alergologia": 38, "cirugia_vascular": 68, "oncologia": 75, "nutricion": 28, "geriatria": 36}},
  {"name": "Clinica del Valle", "type": "private", "network": "bmi_red", "zone": "Quito", "lat": -0.2050, "lon": -78.4920, "specialty_costs": {"cardiologia": 48, "neumologia": 38, "medicina_general": 28, "emergencias": 52, "gastroenterologia": 35, "ortopedia": 35, "neurologia": 44, "urologia": 38, "dermatologia": 30, "pediatria": 24, "ginecologia": 32, "oftalmologia": 34, "endocrinologia": 34}},
  {"name": "Hospital Verdi Cevallos", "type": "iess", "network": "iess", "zone": "Guayaquil", "lat": -2.1700, "lon": -79.9200, "specialty_costs": {"cardiologia": 0, "neumologia": 0, "medicina_general": 0, "emergencias": 0, "gastroenterologia": 0, "ortopedia": 0, "neurologia": 0, "urologia": 0, "cirugia_general": 0, "pediatria": 0}},
  {"name": "Hospital Guayaquil", "type": "iess", "network": "iess", "zone": "Guayaquil", "lat": -2.1850, "lon": -79.9050, "specialty_costs": {"cardiologia": 0, "neumologia": 0, "medicina_general": 0, "emergencias": 0, "cirugia_general": 0, "ginecologia": 0}},
  {"name": "Clinica Kennedy", "type": "private", "network": "bupa_red_interna", "zone": "Guayaquil", "lat": -2.1600, "lon": -79.9000, "specialty_costs": {"cardiologia": 45, "neumologia": 38, "medicina_general": 25, "emergencias": 50, "gastroenterologia": 35, "ortopedia": 35, "neurologia": 40, "urologia": 38, "dermatologia": 30, "pediatria": 22, "ginecologia": 30, "oftalmologia": 32, "otorrinolaringologia": 30, "psiquiatria": 38, "endocrinologia": 35}},
  {"name": "Clinica Alemana", "type": "private", "network": "saludsa_red", "zone": "Guayaquil", "lat": -2.1750, "lon": -79.8850, "specialty_costs": {"cardiologia": 50, "neumologia": 40, "medicina_general": 30, "emergencias": 55, "gastroenterologia": 38, "ortopedia": 38, "neurologia": 45, "urologia": 42, "dermatologia": 34, "pediatria": 26, "ginecologia": 35, "oftalmologia": 36}},
  {"name": "Hospital Rodolfo Robles", "type": "iess", "network": "iess", "zone": "Guayaquil", "lat": -2.1550, "lon": -79.9100, "specialty_costs": {"cardiologia": 0, "neumologia": 0, "medicina_general": 0, "emergencias": 0, "neurologia": 0, "cirugia_general": 0}},
  {"name": "Hospital Abel Gilbert", "type": "iess", "network": "iess", "zone": "Guayaquil", "lat": -2.1680, "lon": -79.8950, "specialty_costs": {"cardiologia": 0, "neumologia": 0, "medicina_general": 0, "emergencias": 0, "gastroenterologia": 0, "ortopedia": 0}},
  {"name": "Hospital IESS Cuenca", "type": "iess", "network": "iess", "zone": "Cuenca", "lat": -2.8974, "lon": -78.9994, "specialty_costs": {"cardiologia": 0, "neumologia": 0, "medicina_general": 0, "emergencias": 0, "gastroenterologia": 0, "ortopedia": 0, "neurologia": 0, "urologia": 0}},
  {"name": "Clinica Santa Ines", "type": "private", "network": "bupa_red_interna", "zone": "Cuenca", "lat": -2.9000, "lon": -78.9900, "specialty_costs": {"cardiologia": 42, "neumologia": 35, "medicina_general": 22, "emergencias": 45, "gastroenterologia": 32, "ortopedia": 32, "neurologia": 38, "urologia": 35, "dermatologia": 28, "pediatria": 20, "ginecologia": 28, "oftalmologia": 30}},
  {"name": "Hospital IESS Loja", "type": "iess", "network": "iess", "zone": "Loja", "lat": -3.9890, "lon": -79.2040, "specialty_costs": {"cardiologia": 0, "neumologia": 0, "medicina_general": 0, "emergencias": 0, "gastroenterologia": 0, "ortopedia": 0}},
  {"name": "Hospital IESS Santo Domingo", "type": "iess", "network": "iess", "zone": "Santo Domingo", "lat": -0.2530, "lon": -79.1670, "specialty_costs": {"cardiologia": 0, "neumologia": 0, "medicina_general": 0, "emergencias": 0, "cirugia_general": 0, "ortopedia": 0}},
  {"name": "Clinica Monte Sinai", "type": "private", "network": "saludsa_red", "zone": "Guayaquil", "lat": -2.1900, "lon": -79.8800, "specialty_costs": {"cardiologia": 46, "neumologia": 37, "medicina_general": 26, "emergencias": 48, "gastroenterologia": 34, "ortopedia": 34, "neurologia": 42, "urologia": 40, "dermatologia": 28, "pediatria": 22, "ginecologia": 30, "oftalmologia": 32}},
  {"name": "Hospital IESS Ambato", "type": "iess", "network": "iess", "zone": "Ambato", "lat": -1.2417, "lon": -78.6197, "specialty_costs": {"cardiologia": 0, "neumologia": 0, "medicina_general": 0, "emergencias": 0, "cirugia_general": 0, "ortopedia": 0, "pediatria": 0}},
  {"name": "Hospital IESS Portoviejo", "type": "iess", "network": "iess", "zone": "Portoviejo", "lat": -1.0538, "lon": -80.4550, "specialty_costs": {"cardiologia": 0, "neumologia": 0, "medicina_general": 0, "emergencias": 0, "cirugia_general": 0}},
  {"name": "Clinica Latina", "type": "private", "network": "bupa_red_interna", "zone": "Quito", "lat": -0.1680, "lon": -78.4580, "specialty_costs": {"cardiologia": 46, "neumologia": 38, "medicina_general": 26, "emergencias": 48, "gastroenterologia": 34, "ortopedia": 34, "neurologia": 42, "urologia": 38, "dermatologia": 30, "pediatria": 24, "ginecologia": 30, "oftalmologia": 34, "otorrinolaringologia": 32, "psiquiatria": 40, "endocrinologia": 36, "alergologia": 32}},
  {"name": "Hospital Jose Carrasco Arteaga", "type": "iess", "network": "iess", "zone": "Cuenca", "lat": -2.9050, "lon": -78.9850, "specialty_costs": {"cardiologia": 0, "neumologia": 0, "medicina_general": 0, "emergencias": 0, "oncologia": 0, "gastroenterologia": 0}}
]